lmdb_object_store/__init__.py
lmdb_object_store/lmdb_object_store.py
lmdb_object_store/py.typed
lmdb_object_store-0.1.0.dist-info/METADATA
lmdb_object_store-0.1.0.dist-info/WHEEL
lmdb_object_store-0.1.0.dist-info/licenses/LICENSE
lmdb_object_store-0.1.0.dist-info/RECORD
