Metadata-Version: 2.4
Name: lmdb-object-store
Version: 0.1.0
Summary: Lightweight LMDB-backed object store for Python
Project-URL: Homepage, https://github.com/yuka30240/lmdb-object-store
Project-URL: Repository, https://github.com/yuka30240/lmdb-object-store
Project-URL: Issues, https://github.com/yuka30240/lmdb-object-store/issues
Project-URL: Changelog, https://github.com/yuka30240/lmdb-object-store/releases
Author-email: yuka30240 <yuuka30240@gmail.com>
Maintainer-email: yuka30240 <yuuka30240@gmail.com>
License: MIT
License-File: LICENSE
Keywords: atomic,database,key-value,lmdb,object-store,thread-safe
Classifier: Development Status :: 4 - Beta
Classifier: Intended Audience :: Developers
Classifier: License :: OSI Approved :: MIT License
Classifier: Operating System :: OS Independent
Classifier: Programming Language :: Python :: 3
Classifier: Programming Language :: Python :: 3.10
Classifier: Programming Language :: Python :: 3.11
Classifier: Programming Language :: Python :: 3.12
Classifier: Topic :: Database
Classifier: Topic :: Software Development :: Libraries :: Python Modules
Classifier: Typing :: Typed
Requires-Python: >=3.10
Requires-Dist: lmdb>=1.7.3
